learn_drama/__init__.py
learn_drama/cli.py
learn_drama/learn_drama.py
learn_drama/text_helper.py
learn_drama-0.0.1a0.dist-info/AUTHORS.rst
learn_drama-0.0.1a0.dist-info/LICENSE
learn_drama-0.0.1a0.dist-info/METADATA
learn_drama-0.0.1a0.dist-info/WHEEL
learn_drama-0.0.1a0.dist-info/entry_points.txt
learn_drama-0.0.1a0.dist-info/top_level.txt
learn_drama-0.0.1a0.dist-info/RECORD
