Metadata-Version: 2.1
Name: learn-drama
Version: 0.0.1a0
Summary: Type and learn drama helper.
Home-page: https://github.com/Boltzmann/learn_drama
Author: Stefan Bollmann
Author-email: stefan.bollmann@rwth-aachen.de
License: GNU General Public License v3
Keywords: learn_drama
Platform: UNKNOWN
Classifier: Development Status :: 2 - Pre-Alpha
Classifier: Intended Audience :: Developers
Classifier: License :: OSI Approved :: GNU General Public License v3 (GPLv3)
Classifier: Natural Language :: English
Classifier: Programming Language :: Python :: 3
Classifier: Programming Language :: Python :: 3.8
Requires-Python: >=3.6
Requires-Dist: Click (>=7.0)
